{
  "EF9595": [20,80,0,0],
  "FACBEA" : [0,0,0,100],
  "D755A5" : [30,0,55,15],
  "35A29F" : [10,30,60,0],
  "FBF0B2" : [0,80,0,20],
  "CAEDFF":[0,0,100,0],
  "662549" :[0,0,10,90],
  "65451F": [40,40,20,0],
  "D25380":[40,0,0,60],
  "E08E6D": [40,60,0,0],
  "D83F31": [60,0,0,40],
  "FC4F00": [20,70,0,10],
  "008170" : [0,100,0,0],
  "068FFF" : [10,0,90,0],
  "00FFF6" : [0,0,10,90],
  "08FFC8": [0,90,10,0],
  "TESTR": [100, 100, 100, 100],
  "TESTY": [0, 1, 0, 0],
  "TESTB": [0, 0, 1, 0],
  "TESTP": [0, 0, 0, 1]
}





